README.rst
setup.py
python_simsimi/__init__.py
python_simsimi/language_codes.py
python_simsimi/response_codes.py
python_simsimi/simsimi.py
python_simsimi.egg-info/PKG-INFO
python_simsimi.egg-info/SOURCES.txt
python_simsimi.egg-info/dependency_links.txt
python_simsimi.egg-info/top_level.txt