Metadata-Version: 1.1
Name: python-simsimi
Version: 1.0
Summary: SimSimi integration for Python
Home-page: http://ferdinandsilva.com
Author: Ferdinand Silva
Author-email: ferdinandsilva@ferdinandsilva.com
License: UNKNOWN
Download-URL: https://github.com/six519/python-simsimi
Platform: UNKNOWN
Classifier: Development Status :: 4 - Beta
Classifier: Intended Audience :: Developers
Classifier: Natural Language :: English
Classifier: Programming Language :: Python
Classifier: License :: Freeware
